CurveMatchingPython/CurveMatchingPython.py
CurveMatchingPython/__init__.py
CurveMatchingPython/test.py
CurveMatchingPython-1.1.7.dist-info/METADATA
CurveMatchingPython-1.1.7.dist-info/WHEEL
CurveMatchingPython-1.1.7.dist-info/top_level.txt
CurveMatchingPython-1.1.7.dist-info/RECORD
