Metadata-Version: 2.1
Name: CurveMatchingPython
Version: 1.1.7
Summary: Python wrapper for CurveMatching  DOI=10.1016/j.combustflame.2016.03.019
Home-page: https://github.com/edoardoramalli/CurveMatchingPython
Author: Edoardo Ramalli
Author-email: edoardo.ramalli@polimi.it
License: UNKNOWN
Platform: UNKNOWN
Classifier: Programming Language :: Python :: 3
Requires-Dist: numpy
